{
  "title": "18м_3гр_2части",
  "segments": [
    {
      "name": "Часть 1",
      "shape": "truncated_pyramid",
      "faces": 3,
      "height": 11.8,
      "levels": 3,
      "base_size": 2.7,
      "top_size": 1.6,
      "sections": [
        {
          "name": "Нижняя",
          "height": 0.0,
          "deviation_x_mm": -0.0,
          "deviation_y_mm": -0.0
        },
        {
          "name": "Секция 2",
          "height": 2.0,
          "deviation_x_mm": -0.34115538033086634,
          "deviation_y_mm": -0.46987046848027103
        },
        {
          "name": "Секция 3",
          "height": 2.0,
          "deviation_x_mm": -0.34115538033086634,
          "deviation_y_mm": -0.46987046848027103
        },
        {
          "name": "Секция 4",
          "height": 2.0,
          "deviation_x_mm": -0.34115538033086634,
          "deviation_y_mm": -0.46987046848027103
        },
        {
          "name": "Секция 5",
          "height": 2.0,
          "deviation_x_mm": -0.34115538033086634,
          "deviation_y_mm": -0.46987046848027103
        },
        {
          "name": "Секция 6",
          "height": 2.0,
          "deviation_x_mm": -0.34115538033086634,
          "deviation_y_mm": -0.46987046848027103
        },
        {
          "name": "Верхняя",
          "height": 1.8000000000000007,
          "deviation_x_mm": -0.3070398422977798,
          "deviation_y_mm": -0.42288342163224407
        }
      ]
    },
    {
      "name": "Часть 2",
      "shape": "prism",
      "faces": 3,
      "height": 6.2,
      "levels": 3,
      "base_size": 1.6,
      "top_size": 1.6,
      "sections": [
        {
          "name": "Нижняя",
          "height": 0.0,
          "deviation_x_mm": 0.0,
          "deviation_y_mm": 0.0
        },
        {
          "name": "Секция 2",
          "height": 2.0,
          "deviation_x_mm": 1.0225052718798675,
          "deviation_y_mm": 0.23626905645682106
        },
        {
          "name": "Секция 3",
          "height": 2.0,
          "deviation_x_mm": 1.0225052718798675,
          "deviation_y_mm": 0.23626905645682106
        },
        {
          "name": "Верхняя",
          "height": 2.2,
          "deviation_x_mm": 1.1247557990678545,
          "deviation_y_mm": 0.2598959621025032
        }
      ]
    }
  ],
  "distance": 32.47,
  "angle": 0.1,
  "instrument_height": 1.61,
  "rotation": 1.2
}